{
  "type": "STANDARD",
  "hasLegacyBackendURL": false,
  "params": {
    "backendEnabled": false,
    "enableJavascriptModules": false,
    "autoStartBackend": false,
    "hideJSSecurityPanel": false,
    "hideWebAppConfig": false,
    "envSelection": {
      "envMode": "INHERIT"
    },
    "nbProcesses": 0,
    "backendAPIAccessEnabled": false,
    "backendFramework": "FLASK",
    "libraries": [
      "jquery",
      "dataiku",
      "leaflet",
      "bootstrap"
    ],
    "infra": {
      "containerSelection": {
        "containerMode": "INHERIT"
      },
      "overrideGlobalK8sExposition": false,
      "exposition": {
        "type": "local_process",
        "params": {}
      },
      "scaling": {
        "initialReplicas": 1,
        "progressDeadlineSeconds": 600,
        "hpa": false,
        "hpaTargetCPUPercent": 0,
        "hpaTargetMemoryPercent": 0,
        "hpaMetrics": [],
        "hpaMinPods": 0,
        "hpaMaxPods": 0,
        "hpaAnnotations": []
      },
      "podDisruptionBudget": {
        "enable": false,
        "isMaxUnavailable": false,
        "minAvailable": "50%"
      },
      "deploymentModifier": {
        "config": {}
      }
    },
    "forceAuthentication": false
  },
  "config": {},
  "name": "Geo Analysis",
  "apiKey": "e:AES:X2:zD/BZoyOFA8i4eZWyKkdRcse8XhfYycgSy2/UE+4t20O3akD7ExrJsxd9AS1OcTsBeEy58NszUGSTUghUmUhj4G24//T0ZDp4XAbwqR8odP60XjemIk1",
  "creationTag": {
    "versionNumber": 0,
    "lastModifiedBy": {
      "login": "gerardkra30@gmail.com"
    },
    "lastModifiedOn": 1768301998223
  },
  "tags": [],
  "checklists": {
    "checklists": []
  },
  "customFields": {},
  "isVirtual": false
}